comform/__init__.py
comform/__main__.py
comform/cli.py
comform/comments.py
comform/fixes.py
comform/py.typed
comform/utils.py
comform/version.py
comform-0.1.1.dist-info/METADATA
comform-0.1.1.dist-info/WHEEL
comform-0.1.1.dist-info/entry_points.txt
comform-0.1.1.dist-info/licenses/LICENSE
comform-0.1.1.dist-info/RECORD
