Metadata-Version: 2.1
Name: comform
Version: 0.1.1
Summary: Python Comment Conformity Formatter
Project-URL: Homepage, https://j-hil@github.com/j-hil/comform
Author-email: j-hil <92876062+j-hil@users.noreply.github.com>
License: GNU General Public License v3 (GPLv3)
License-File: LICENSE
Keywords: automation,comments,formatter
Classifier: Development Status :: 3 - Alpha
Classifier: License :: OSI Approved :: GNU General Public License v3 (GPLv3)
Classifier: Operating System :: OS Independent
Classifier: Programming Language :: Python :: 3 :: Only
Classifier: Topic :: Software Development :: Libraries :: Python Modules
Classifier: Topic :: Software Development :: Quality Assurance
Requires-Dist: mdformat<1,>=0.7.16
Requires-Dist: pathspec<1,>=0.11
Requires-Dist: tomli<3,>=2; python_version < '3.11'
Provides-Extra: dev
Requires-Dist: autoflake<3,>=2; extra == 'dev'
Requires-Dist: black<24,>=23; extra == 'dev'
Requires-Dist: build<1,>=0.9.0; extra == 'dev'
Requires-Dist: coverage[toml]<8,>=7; extra == 'dev'
Requires-Dist: flake8-pyproject<2,>=1.2; extra == 'dev'
Requires-Dist: ipykernel<7,>=6.21; extra == 'dev'
Requires-Dist: ipython<9,>=8.10; extra == 'dev'
Requires-Dist: isort<6,>=5.12; extra == 'dev'
Requires-Dist: mypy<2,>=1; extra == 'dev'
Requires-Dist: pre-commit<4,>=3; extra == 'dev'
Requires-Dist: pydocstringformatter<1,>=0.7.2; extra == 'dev'
Requires-Dist: pydocstyle[toml]<7,>=6.3; extra == 'dev'
Requires-Dist: pylint<3,>=2.16; extra == 'dev'
Requires-Dist: pytest<8,>=7.2; extra == 'dev'
Requires-Dist: twine<5,>=4.0.1; extra == 'dev'
